setup.py
guardrails/__init__.py
guardrails/cli.py
guardrails/datatypes.py
guardrails/document_store.py
guardrails/embedding.py
guardrails/guard.py
guardrails/llm_providers.py
guardrails/logging_utils.py
guardrails/rail.py
guardrails/run.py
guardrails/schema.py
guardrails/validators.py
guardrails/version.py
guardrails/applications/__init__.py
guardrails/applications/text2sql.py
guardrails/prompt/__init__.py
guardrails/prompt/base_prompt.py
guardrails/prompt/instructions.py
guardrails/prompt/prompt.py
guardrails/utils/__init__.py
guardrails/utils/constants.py
guardrails/utils/docs_utils.py
guardrails/utils/logs_utils.py
guardrails/utils/misc.py
guardrails/utils/pydantic_utils.py
guardrails/utils/reask_utils.py
guardrails/utils/sql_utils.py
guardrails_ct.egg-info/PKG-INFO
guardrails_ct.egg-info/SOURCES.txt
guardrails_ct.egg-info/dependency_links.txt
guardrails_ct.egg-info/entry_points.txt
guardrails_ct.egg-info/requires.txt
guardrails_ct.egg-info/top_level.txt