Metadata-Version: 2.1
Name: guardrails-ct
Version: 1.2
Summary: Adding guardrails to large language models.
Home-page: https://github.com/shreyar/guardrails
Author: Shreya Rajpal
Author-email: shreya.rajpal@gmail.com
License: Apache 2.0
Platform: UNKNOWN
Classifier: Programming Language :: Python
Classifier: Programming Language :: Python :: 3
Classifier: Programming Language :: Python :: 3.6
Classifier: Topic :: Scientific/Engineering :: Artificial Intelligence
Requires-Python: >=3.7.0
Provides-Extra: dev
Provides-Extra: manifest
Provides-Extra: profanity
Provides-Extra: critique
